Metadata-Version: 2.1
Name: english-words
Version: 1.0.4
Summary: Contains sets of english words
Home-page: https://github.com/mwiens91/english-words-py
Author: Matt Wiens
Author-email: mwiens91@gmail.com
License: MIT
Platform: UNKNOWN
Classifier: Development Status :: 5 - Production/Stable
Classifier: License :: OSI Approved :: MIT License
Classifier: Natural Language :: English
Classifier: Programming Language :: Python
